quart_i18n/__init__.py
quart_i18n/errors.py
quart_i18n/localization.py
quart_i18n-0.1.0.dist-info/licenses/LICENSE
quart_i18n-0.1.0.dist-info/METADATA
quart_i18n-0.1.0.dist-info/WHEEL
quart_i18n-0.1.0.dist-info/top_level.txt
quart_i18n-0.1.0.dist-info/RECORD
