Metadata-Version: 2.4
Name: quart-i18n
Version: 0.1.0
Summary: Internationalization (i18n) extension for Quart applications.
Home-page: https://github.com/1bali1/quart-i18n
Author: 1bali1
Author-email: Bali <info@1bali1.hu>
License: MIT
Project-URL: Homepage, https://github.com/1bali1/quart-i18n
Project-URL: Documentation, https://github.com/1bali1/quart-i18n#readme
Project-URL: Repository, https://github.com/1bali1/quart-i18n
Project-URL: Issues, https://github.com/1bali1/quart-i18n/issues
Keywords: quart,i18n,internationalization,localization,translation
Classifier: Intended Audience :: Developers
Classifier: License :: OSI Approved :: MIT License
Classifier: Programming Language :: Python
Classifier: Programming Language :: Python :: 3
Classifier: Programming Language :: Python :: 3.10
Classifier: Programming Language :: Python :: 3.11
Classifier: Programming Language :: Python :: 3.12
Classifier: Topic :: Software Development :: Internationalization
Classifier: Topic :: Software Development :: Localization
Requires-Python: >=3.10
License-File: LICENSE
Requires-Dist: quart>=0.18.0
Provides-Extra: dev
Requires-Dist: pytest; extra == "dev"
Requires-Dist: pytest-asyncio; extra == "dev"
Requires-Dist: ruff; extra == "dev"
Requires-Dist: black; extra == "dev"
Requires-Dist: mypy; extra == "dev"
Requires-Dist: build; extra == "dev"
Requires-Dist: twine; extra == "dev"
Dynamic: author
Dynamic: home-page
Dynamic: license-file
Dynamic: requires-python
